alembic_pilot/__init__.py
alembic_pilot/alembic.py
alembic_pilot/db_connection.py
alembic_pilot/exceptions.py
alembic_pilot/import_utils.py
alembic_pilot/managed_database.py
alembic_pilot/py.typed
alembic_pilot/sanity_checks.py
alembic_pilot/data/alembic.ini.mako
alembic_pilot/data/env.py.mako
alembic_pilot/data/script.mako
alembic_pilot-0.1.3.dist-info/METADATA
alembic_pilot-0.1.3.dist-info/WHEEL
alembic_pilot-0.1.3.dist-info/licenses/LICENSE
alembic_pilot-0.1.3.dist-info/RECORD
