Metadata-Version: 2.4
Name: alembic-pilot
Version: 0.1.3
Summary: A powerful database migration management tool built on top of Alembic, supporting AWS, Azure, Google Cloud, and Heroku PostgreSQL deployments
Project-URL: Homepage, https://github.com/jtbeach/alembic-pilot
Project-URL: Documentation, https://github.com/jtbeach/alembic-pilot#readme
Project-URL: Repository, https://github.com/jtbeach/alembic-pilot.git
Project-URL: Issues, https://github.com/jtbeach/alembic-pilot/issues
Author-email: Joel Beach <12853460+jtbeach@users.noreply.github.com>
License: MIT
License-File: LICENSE
Keywords: alembic,aws,azure,database,gcp,heroku,migrations,postgresql,sqlalchemy
Classifier: Development Status :: 4 - Beta
Classifier: Intended Audience :: Developers
Classifier: License :: OSI Approved :: MIT License
Classifier: Programming Language :: Python :: 3
Classifier: Programming Language :: Python :: 3.12
Classifier: Topic :: Database
Classifier: Topic :: Software Development :: Libraries :: Python Modules
Requires-Python: >=3.12
Requires-Dist: alembic>=1.15.2
Requires-Dist: psycopg-toolbox>=0.1.3
Requires-Dist: psycopg>=3.2.9
Requires-Dist: sqlalchemy[asyncio,postgresql-psycopg]>=2.0.41
